
    {
        "name": "Burger Joint",
        "description": "Best burgers in town",
        "address": "123 Main St, Springfield",
        "location": { "type": "Point", "coordinates": [-77.0369, 38.9072] },
        "rating": 4.5,
        "imageUrl": "https://images.unsplash.com/photo-1550547660-d9450f859349?ixlib=rb-1.2.1&auto=format&fit=crop&w=800&q=80",
        "ownerId": "mock-owner-1",
        "cuisineType": "American",
        "openingTime": "10:00 AM",
        "closingTime": "10:00 PM",
        "isOpen": true
    },
    {
        "name": "Pizzeria Napoli",
        "description": "Authentic Italian pizza",
        "address": "456 Oak Avenue, Springfield",
        "location": { "type": "Point", "coordinates": [-77.0359, 38.9082] },
        "rating": 4.8,
        "imageUrl": "https://images.unsplash.com/photo-1513104890138-7c749659a591?ixlib=rb-1.2.1&auto=format&fit=crop&w=800&q=80",
        "ownerId": "mock-owner-2",
        "cuisineType": "Italian",
        "openingTime": "11:00 AM",
        "closingTime": "11:00 PM",
        "isOpen": true
    },
    {
        "name": "Sushi Zen",
        "description": "Fresh sushi and sashmini daily",
        "address": "789 Pine Road, Springfield",
        "location": { "type": "Point", "coordinates": [-77.0349, 38.9092] },
        "rating": 4.7,
        "imageUrl": "https://images.unsplash.com/photo-1579871494447-9811cf80d66c?ixlib=rb-1.2.1&auto=format&fit=crop&w=800&q=80",
        "ownerId": "mock-owner-3",
        "cuisineType": "Japanese",
        "openingTime": "12:00 PM",
        "closingTime": "10:30 PM",
        "isOpen": false
    },
    {
        "name": "Taco Fiesta",
        "description": "Spicy and authentic Mexican street food",
        "address": "321 Elm Street, Springfield",
        "location": { "type": "Point", "coordinates": [-77.0379, 38.9062] },
        "rating": 4.3,
        "imageUrl": "https://images.unsplash.com/photo-1565299585323-38d6b0865b47?ixlib=rb-1.2.1&auto=format&fit=crop&w=800&q=80",
        "ownerId": "mock-owner-4",
        "cuisineType": "Mexican",
        "openingTime": "09:00 AM",
        "closingTime": "09:00 PM",
        "isOpen": true
    },
    {
        "name": "Green Bowl Salads",
        "description": "Healthy and organic salad bowls",
        "address": "555 Cedar Lane, Springfield",
        "location": { "type": "Point", "coordinates": [-77.0389, 38.9052] },
        "rating": 4.6,
        "imageUrl": "https://images.unsplash.com/photo-1512621776951-a57141f2eefd?ixlib=rb-1.2.1&auto=format&fit=crop&w=800&q=80",
        "ownerId": "mock-owner-5",
        "cuisineType": "Healthy",
        "openingTime": "08:00 AM",
        "closingTime": "08:00 PM",
        "isOpen": true
    },
    {
        "name": "The Curry House",
        "description": "Authentic Indian curries and naan",
        "address": "101 Curry Lane, Springfield",
        "location": { "type": "Point", "coordinates": [-77.0400, 38.9040] },
        "rating": 4.7,
        "imageUrl": "https://images.unsplash.com/photo-1585937421612-70a008356fbe?auto=format&fit=crop&w=800&q=80",
        "ownerId": "mock-owner-6",
        "cuisineType": "Indian",
        "openingTime": "11:00 AM",
        "closingTime": "10:30 PM",
        "isOpen": true
    },
    {
        "name": "Baguette & Co.",
        "description": "Freshly baked French breads and pastries",
        "address": "202 Baker St, Springfield",
        "location": { "type": "Point", "coordinates": [-77.0410, 38.9030] },
        "rating": 4.8,
        "imageUrl": "https://images.unsplash.com/photo-1608198093002-ad4e005484ec?auto=format&fit=crop&w=800&q=80",
        "ownerId": "mock-owner-7",
        "cuisineType": "French",
        "openingTime": "07:00 AM",
        "closingTime": "06:00 PM",
        "isOpen": true
    },
    {
        "name": "Dragon Wok",
        "description": "Delicious Chinese stir-fries and noodles",
        "address": "303 Dragon Blvd, Springfield",
        "location": { "type": "Point", "coordinates": [-77.0420, 38.9020] },
        "rating": 4.4,
        "imageUrl": "https://images.unsplash.com/photo-1540189549336-e6e99c3679fe?auto=format&fit=crop&w=800&q=80",
        "ownerId": "mock-owner-8",
        "cuisineType": "Chinese",
        "openingTime": "11:00 AM",
        "closingTime": "10:00 PM",
        "isOpen": true
    },
    {
        "name": "Texas BBQ Grill",
        "description": "Slow-smoked ribs and brisket",
        "address": "404 Smoke Rd, Springfield",
        "location": { "type": "Point", "coordinates": [-77.0430, 38.9010] },
        "rating": 4.9,
        "imageUrl": "https://images.unsplash.com/photo-1529193591184-b1d58069ecdd?auto=format&fit=crop&w=800&q=80",
        "ownerId": "mock-owner-9",
        "cuisineType": "BBQ",
        "openingTime": "12:00 PM",
        "closingTime": "09:00 PM",
        "isOpen": true
    },
    {
        "name": "Vegan Delights",
        "description": "100% plant-based healthy meals",
        "address": "505 Plant Ave, Springfield",
        "location": { "type": "Point", "coordinates": [-77.0440, 38.9000] },
        "rating": 4.6,
        "imageUrl": "https://images.unsplash.com/photo-1511690656952-34342bb7c2f2?auto=format&fit=crop&w=800&q=80",
        "ownerId": "mock-owner-10",
        "cuisineType": "Vegan",
        "openingTime": "09:00 AM",
        "closingTime": "08:00 PM",
        "isOpen": true
    },
    {
        "name": "Seafood Catch",
        "description": "Fresh ocean catches daily",
        "address": "606 Harbor Way, Springfield",
        "location": { "type": "Point", "coordinates": [-77.0450, 38.8990] },
        "rating": 4.5,
        "imageUrl": "https://images.unsplash.com/photo-1615141982883-c7ad0e69fd62?auto=format&fit=crop&w=800&q=80",
        "ownerId": "mock-owner-11",
        "cuisineType": "Seafood",
        "openingTime": "11:30 AM",
        "closingTime": "10:00 PM",
        "isOpen": true
    },
    {
        "name": "Mediterranean Grill",
        "description": "Shawarma, hummus, and falafel",
        "address": "707 Olive St, Springfield",
        "location": { "type": "Point", "coordinates": [-77.0460, 38.8980] },
        "rating": 4.7,
        "imageUrl": "https://images.unsplash.com/photo-1542314831-c6a4d142997b?auto=format&fit=crop&w=800&q=80",
        "ownerId": "mock-owner-12",
        "cuisineType": "Mediterranean",
        "openingTime": "10:00 AM",
        "closingTime": "09:30 PM",
        "isOpen": true
    },
    {
        "name": "Seoul BBQ",
        "description": "Korean tabletop grilling",
        "address": "808 Kimchi Blvd, Springfield",
        "location": { "type": "Point", "coordinates": [-77.0470, 38.8970] },
        "rating": 4.8,
        "imageUrl": "https://images.unsplash.com/photo-1580651315530-69c8e0026377?auto=format&fit=crop&w=800&q=80",
        "ownerId": "mock-owner-13",
        "cuisineType": "Korean",
        "openingTime": "12:00 PM",
        "closingTime": "11:00 PM",
        "isOpen": true
    },
    {
        "name": "Pancake World",
        "description": "All-day breakfast and fluffy pancakes",
        "address": "909 Maple Dr, Springfield",
        "location": { "type": "Point", "coordinates": [-77.0480, 38.8960] },
        "rating": 4.3,
        "imageUrl": "https://images.unsplash.com/photo-1528207776546-365bb710ee93?auto=format&fit=crop&w=800&q=80",
        "ownerId": "mock-owner-14",
        "cuisineType": "Breakfast",
        "openingTime": "06:00 AM",
        "closingTime": "03:00 PM",
        "isOpen": true
    },
    {
        "name": "Gelato Heaven",
        "description": "Handcrafted Italian gelato",
        "address": "1010 Sweet Rd, Springfield",
        "location": { "type": "Point", "coordinates": [-77.0490, 38.8950] },
        "rating": 4.9,
        "imageUrl": "https://images.unsplash.com/photo-1563805042-7684c8e9e1cb?auto=format&fit=crop&w=800&q=80",
        "ownerId": "mock-owner-15",
        "cuisineType": "Dessert",
        "openingTime": "12:00 PM",
        "closingTime": "11:00 PM",
        "isOpen": true
    }
]
